mumobo/__init__.py
mumobo/mumobo.py
mumobo-0.0.4.dist-info/METADATA
mumobo-0.0.4.dist-info/WHEEL
mumobo-0.0.4.dist-info/top_level.txt
mumobo-0.0.4.dist-info/RECORD
