Metadata-Version: 2.4
Name: mumobo
Version: 0.0.4
Summary: API for the mumobo device
Home-page: https://gitlab.phys.ethz.ch/code/experiment/mumobo
Author: Maurice Friedrichs
Author-email: huberse@phys.ethz.ch
Requires-Python: >=3.8
Dynamic: author
Dynamic: author-email
Dynamic: description
Dynamic: description-content-type
Dynamic: home-page
Dynamic: requires-python
Dynamic: summary
